[
    {
        "originUrl": "https://www.google.com/search?q=shorten+url+js&sxsrf=ALeKk01FTQ9vZ79AM08LYiA9hlxvRc-HVQ:1614693155750&source=lnms&tbm=vid&sa=X&ved=2ahUKEwjeteDf4JHvAhUCCxoKHckoDDA4ChD8BSgCegQIBRAE&biw=1920&bih=937",
        "shrinkUrl": "OSCdOhTDZ",
        "createAt": "05/03/2021, 9:20:57",
        "redirectCounter": 1
    },
    {
        "originUrl": "https://expressjs.com/en/guide/routing.html",
        "shrinkUrl": "ylacx6A9L",
        "createAt": "05/03/2021, 9:30:11",
        "redirectCounter": 0
    },
    {
        "originUrl": "https://www.google.com/",
        "shrinkUrl": "guJAIH63m",
        "createAt": "05/03/2021, 9:30:54",
        "redirectCounter": 1
    },
    {
        "originUrl": "https://github.com/Jiano1211/URL-sashortener/blob/dev/README.md",
        "shrinkUrl": "ooBjYD1gW",
        "createAt": "05/03/2021, 10:10:47",
        "redirectCounter": 0
    },
    {
        "originUrl": "https://github.com/Jianogg1211/URL-sashortener/blob/dev/README.md",
        "shrinkUrl": "8VMf3ZG5c",
        "createAt": "05/03/2021, 10:12:37",
        "redirectCounter": 0
    },
    {
        "originUrl": "https://github.com/hjh/URL-sashortener/blob/dev/README.md",
        "shrinkUrl": "K5z1y4Cif",
        "createAt": "05/03/2021, 10:14:09",
        "redirectCounter": 0
    },
    {
        "originUrl": "https://github.com/hjh/URL-sashortegner/blob/dev/README.md",
        "shrinkUrl": "f-D-yyWtC",
        "createAt": "05/03/2021, 10:20:46",
        "redirectCounter": 0
    },
    {
        "originUrl": "https://github.com/hjh/URL-sashohhhrtegner/blob/dev/README.md",
        "shrinkUrl": "9VLhIzI5r",
        "createAt": "05/03/2021, 10:22:20",
        "redirectCounter": 0
    },
    {
        "originUrl": "https://github.com/hjh/URLhohhhrtegner/blob/dev/README.md",
        "shrinkUrl": "hN9gdc9Ww",
        "createAt": "05/03/2021, 10:23:28",
        "redirectCounter": 0
    },
    {
        "originUrl": "https://github.com/hjh/Urtegner/blob/dev/README.md",
        "shrinkUrl": "0McwePlwp",
        "createAt": "05/03/2021, 10:27:58",
        "redirectCounter": 0
    },
    {
        "originUrl": "https://github.com/dfgdg/Urtegner/blob/dev/README.md",
        "shrinkUrl": "9Q3a8LMXw",
        "createAt": "05/03/2021, 11:12:18",
        "redirectCounter": 0
    },
    {
        "originUrl": "https://github.cosm/dfgdg/Urtegner/blob/dev/README.md",
        "shrinkUrl": "qayFRyoKv",
        "createAt": "05/03/2021, 11:15:06",
        "redirectCounter": 0
    },
    {
        "originUrl": "https://github.cosm/dfgdg/Urteghhner/blob/dev/README.md",
        "shrinkUrl": "xc_upsXWn",
        "createAt": "05/03/2021, 11:35:46",
        "redirectCounter": 0
    }
]